pioreactor_high_temp_plugin/__init__.py
pioreactor_high_temp_plugin-0.3.0.dist-info/LICENSE
pioreactor_high_temp_plugin-0.3.0.dist-info/METADATA
pioreactor_high_temp_plugin-0.3.0.dist-info/WHEEL
pioreactor_high_temp_plugin-0.3.0.dist-info/entry_points.txt
pioreactor_high_temp_plugin-0.3.0.dist-info/top_level.txt
pioreactor_high_temp_plugin-0.3.0.dist-info/RECORD
