Metadata-Version: 2.1
Name: pioreactor-high-temp-plugin
Version: 0.3.0
Summary: Using this risks damaging your Pioreactor or harming yourself. Only use with the high-temp plastics provided.
Home-page: https://github.com/Pioreactor/pioreactor-high-temp-plugin
Author: Pioreactor
Author-email: cam@pioreactor.com
License: MIT
License-File: LICENSE
